eventpy/__init__.py
eventpy/callbacklist.py
eventpy/eventdispatcher.py
eventpy/eventqueue.py
eventpy/lock.py
eventpy/policy.py
eventpy/internal/__init__.py
eventpy/internal/linkedlist.py
eventpy/internal/lockguard.py
eventpy-0.0.1.dist-info/METADATA
eventpy-0.0.1.dist-info/WHEEL
eventpy-0.0.1.dist-info/license
eventpy-0.0.1.dist-info/top_level.txt
eventpy-0.0.1.dist-info/RECORD
