Metadata-Version: 2.1
Name: eventpy
Version: 0.0.1
Summary: eventpy is a Python event library that provides tools that enable your application components to communicate with each other by dispatching events and listening for them. With eventpy you can easily implement signal/slot mechanism, or observer pattern.
Home-page: https://github.com/wqking/eventpy
Author: wqking
Author-email: wqking@NOSPAMoutlook.com
License: UNKNOWN
Platform: any
Classifier: Programming Language :: Python :: 3
Classifier: License :: OSI Approved :: Apache Software License
Classifier: Operating System :: OS Independent
Requires-Python: >=3.6
